openimageio-3.1.9.0.dist-info/RECORD
openimageio-3.1.9.0.dist-info/WHEEL
openimageio-3.1.9.0.dist-info/entry_points.txt
openimageio-3.1.9.0.dist-info/METADATA
openimageio-3.1.9.0.dist-info/licenses/LICENSE.md
openimageio-3.1.9.0.dist-info/licenses/THIRD-PARTY.md
OpenImageIO/OpenImageIO.cpython-314-darwin.so
OpenImageIO/__init__.pyi
OpenImageIO/__init__.py
OpenImageIO/py.typed
OpenImageIO/bin/maketx
OpenImageIO/bin/oiiotool
OpenImageIO/lib/libOpenImageIO.3.1.9.dylib
OpenImageIO/lib/libOpenImageIO_Util.3.1.9.dylib
OpenImageIO/share/fonts/OpenImageIO/DroidSansMono.ttf
OpenImageIO/share/fonts/OpenImageIO/DroidSans.ttf
OpenImageIO/share/fonts/OpenImageIO/DroidSans-Bold.ttf
OpenImageIO/share/fonts/OpenImageIO/DroidSerif-Italic.ttf
OpenImageIO/share/fonts/OpenImageIO/DroidSerif.ttf
OpenImageIO/share/fonts/OpenImageIO/DroidSerif-BoldItalic.ttf
OpenImageIO/share/fonts/OpenImageIO/DroidSerif-Bold.ttf
