Metadata-Version: 2.1
Name: OpenImageIO
Version: 3.1.9.0
Summary: Reading, writing, and processing images in a wide variety of file formats, using a format-agnostic API, aimed at VFX applications.
Author-Email: Larry Gritz <lg@larrygritz.com>, OpenImageIO Contributors <oiio-dev@lists.aswf.io>
Maintainer-Email: OpenImageIO Contributors <oiio-dev@lists.aswf.io>
License: Apache-2.0
Classifier: Natural Language :: English
Classifier: Operating System :: OS Independent
Classifier: Programming Language :: Python :: 3
Classifier: Programming Language :: Python :: 3.9
Classifier: Programming Language :: Python :: 3.10
Classifier: Programming Language :: Python :: 3.11
Classifier: Programming Language :: Python :: 3.12
Classifier: Programming Language :: Python :: 3.13
Classifier: Programming Language :: Python :: 3.14
Classifier: License :: OSI Approved :: Apache Software License
Classifier: Topic :: Multimedia :: Graphics
Classifier: Topic :: Multimedia :: Video
Classifier: Topic :: Multimedia :: Video :: Display
Classifier: Topic :: Software Development :: Libraries :: Python Modules
Project-URL: Homepage, https://openimageio.org/
Project-URL: Source, https://github.com/AcademySoftwareFoundation/OpenImageIO
Project-URL: Documentation, https://docs.openimageio.org
Project-URL: Issues, https://github.com/AcademySoftwareFoundation/OpenImageIO/issues
Requires-Python: >=3.9
Requires-Dist: numpy<3,>=2.0
